politweet/__init__.py
politweet/scraper.py
politweet-0.0.4.dist-info/LICENSE
politweet-0.0.4.dist-info/METADATA
politweet-0.0.4.dist-info/WHEEL
politweet-0.0.4.dist-info/top_level.txt
politweet-0.0.4.dist-info/RECORD
